Workbook

Sheet Dashboard
A1: AI Factory Dashboard — 32x Vera Rubin NVL72, Abu Dhabi
A2: Headline KPIs, all live-linked; edit assumptions on 'Control Panel & Inputs'
A4: KPI | B4: Value | C4: Unit | D4: Source Sheet
A5: Equity IRR (5-Yr, levered) | B5: ='5Yr Pro Forma Financials'!B36 -> 1.2650683 | C5: % | D5: 5Yr Pro Forma Financials
A6: Project IRR (5-Yr, unlevered) | B6: ='5Yr Pro Forma Financials'!B37 -> 0.3754892 | C6: % | D6: 5Yr Pro Forma Financials
A7: Equity NPV @ hurdle rate | B7: ='5Yr Pro Forma Financials'!B38 -> 1.0980924e+08 | C7: USD | D7: 5Yr Pro Forma Financials
A8: MOIC | B8: ='5Yr Pro Forma Financials'!B39 -> 7.6252854 | C8: x | D8: 5Yr Pro Forma Financials
A9: Payback Period | B9: ='5Yr Pro Forma Financials'!B40 -> 0.8830065 | C9: years | D9: 5Yr Pro Forma Financials
A10: Year 1 Gross Revenue | B10: ='5Yr Pro Forma Financials'!C$8 -> 75600000 | C10: USD | D10: 5Yr Pro Forma Financials
A11: Year 1 EBITDA | B11: ='5Yr Pro Forma Financials'!C$14 -> 60755550 | C11: USD | D11: 5Yr Pro Forma Financials
A12: Year 1 EBITDA Margin | B12: ='5Yr Pro Forma Financials'!C$15 -> 0.80364485 | C12: % | D12: 5Yr Pro Forma Financials
A13: Minimum DSCR | B13: ='5Yr Pro Forma Financials'!B41 -> 2.2623709 | C13: x | D13: 5Yr Pro Forma Financials
A14: Peak MLC vs ASHRAE 90.4 | B14: ='Thermal Hydraulics & MLC'!$B$18 -> 0.077831559 | C14: (limit 0.260) | D14: Thermal Hydraulics & MLC
A15: MLC Compliance Margin | B15: ='Thermal Hydraulics & MLC'!$B$20 -> 0.70064785 | C15: % | D15: Thermal Hydraulics & MLC
A16: Annual Facility Energy | B16: ='Thermal Hydraulics & MLC'!$B$23 -> 66124.161 | C16: MWh/yr | D16: Thermal Hydraulics & MLC
A17: Annual Carbon Emissions | B17: ='Thermal Hydraulics & MLC'!$B$25 -> 25788.423 | C17: tCO2/yr | D17: Thermal Hydraulics & MLC
A18: Annual Water Consumption | B18: ='Thermal Hydraulics & MLC'!$B$24 -> 9918.6242 | C18: m³/yr | D18: Thermal Hydraulics & MLC
A19: Total GPU Count | B19: ='Unit Economics & KPIs'!B5 -> 2304 | C19: GPUs | D19: Unit Economics & KPIs
A20: CapEx per GPU | B20: ='Unit Economics & KPIs'!B11 -> 60546.875 | C20: $/GPU | D20: Unit Economics & KPIs
A21: Blended Revenue per Sold GPU-hour | B21: ='Unit Economics & KPIs'!B8 -> 5.013238 | C21: $/GPU-hr | D21: Unit Economics & KPIs
A22: Cash Cost per M Tokens | B22: ='Unit Economics & KPIs'!B16 -> 0.13786986 | C22: $/M tok | D22: Unit Economics & KPIs
A23: Energy Cost as % of Revenue | B23: ='Unit Economics & KPIs'!B17 -> 0.047289497 | C23: % | D23: Unit Economics & KPIs
A24: Breakeven Power Tariff | B24: ='Unit Economics & KPIs'!B18 -> 1.1247279 | C24: $/kWh | D24: Unit Economics & KPIs

Sheet Control Panel & Inputs
A1: NVIDIA Vera Rubin NVL72 AI Factory — Abu Dhabi
A2: Master Control Panel — edit only the yellow Value cells; every other sheet recalculates from them
A4: Category | B4: Parameter | C4: Value | D4: Unit | E4: Notes / Constraints
A5: Geographic & Climate | B5: Geo_Location | C5: Abu Dhabi, UAE | E5: ASHRAE Climate Zone 1A
A6: Geographic & Climate | B6: Peak_Ambient_DryBulb | C6: 50 | D6: °C | E6: Extreme peak dry-bulb temperature
A7: Geographic & Climate | B7: Coincident_WetBulb | C7: 30 | D7: °C | E7: Peak summer wet-bulb condition
A8: Geographic & Climate | B8: Grid_Carbon_Intensity | C8: 0.39 | D8: kgCO2/kWh | E8: Assumption: Abu Dhabi grid avg (Barakah nuclear + gas + solar mix)
A9: Geographic & Climate | B9: Water_Usage_Effectiveness | C9: 0.15 | D9: L/kWh | E9: Assumption: closed-loop dry coolers, minimal adiabatic assist
A10: Technical Specs | B10: Rack_Count | C10: 32 | D10: racks | E10: Vera Rubin NVL72 racks
A11: Technical Specs | B11: GPUs_Per_Rack | C11: 72 | D11: GPUs | E11: NVL72 = 72 Rubin GPUs per rack
A12: Technical Specs | B12: Peak_Power_Per_Rack | C12: 227 | D12: kW | E12: Compute & scale-up busbar load
A13: Technical Specs | B13: Air_Cooled_Load | C13: 1000 | D13: kW | E13: 1.0 MW network & NVMe storage
A14: Technical Specs | B14: Liquid_Supply_Temp_FWS | C14: 45 | D14: °C | E14: S45 direct-to-chip loop
A15: Technical Specs | B15: Target_Annualized_PUE | C15: 1.08 | E15: Drives facility energy = IT energy x PUE
A16: Technical Specs | B16: Cluster_Utilization | C16: 0.85 | D16: % | E16: Assumption: avg power/capacity utilization of the fleet
A17: Technical Specs | B17: Uptime_Availability | C17: 0.995 | D17: % | E17: Assumption: contractual availability SLA
A18: Technical Specs | B18: Tokens_Per_GPU_Sec | C18: 1800 | D18: tok/s/GPU | E18: Assumption: blended inference throughput per Rubin GPU
A19: Technical Specs | B19: Token_Fleet_Share | C19: 0.3 | D19: % | E19: Share of fleet serving the API token market
A20: Financial & Fiscal | B20: Electricity_Tariff | C20: 0.06 | D20: $/kWh | E20: Abu Dhabi industrial rate (Year 1)
A21: Financial & Fiscal | B21: Tariff_Escalation | C21: 0.02 | D21: %/yr | E21: Assumption: annual power price escalation
A22: Financial & Fiscal | B22: CapEx_Initial | C22: 139500000 | D22: USD | E22: Total turnkey deployment
A23: Financial & Fiscal | B23: Residual_Value_Pct | C23: 0.1 | D23: % | E23: Assumption: pre-tax residual recovery of CapEx at end of Year 5
A24: Financial & Fiscal | B24: Debt_Ratio | C24: 0.8 | D24: % | E24: User adjustable (50% - 80%)
A25: Financial & Fiscal | B25: Interest_Rate | C25: 0.065 | D25: % | E25: Senior debt facility rate
A26: Financial & Fiscal | B26: Debt_Tenor | C26: 5 | D26: Years | E26: Annual amortization schedule
A27: Financial & Fiscal | B27: UAE_Corporate_Tax | C27: 0.09 | D27: % | E27: Statutory corporate tax rate
... A37: Revenue Strategy | B37: Token_Volume_Growth | C37: 0.25 | D37: %/yr | E37: Token demand growth (partially offsets price decline)
A39: Legend: yellow cells with blue text are the editable inputs; all other cells in this workbook are formulas.
A40: Rows marked 'Assumption' are user-supplied estimates, not sourced market data — revisit before investment use.

Sheet Thermal Hydraulics & MLC
A1: Thermal Hydraulics & ASHRAE 90.4 Compliance Engine
A2: S45 closed-loop fluid dynamics, 3-stage trim cooling, and annual energy / water / carbon footprint
A4: Metric / Calculation Step | B4: Value | C4: Unit | D4: Notes
A5: Compute IT Load | B5: ='Control Panel & Inputs'!$C$10*'Control Panel & Inputs'!$C$12 -> 7264 | C5: kW | D5: Racks x kW/rack
A6: Network & Storage Air Load | B6: ='Control Panel & Inputs'!$C$13 -> 1000 | C6: kW | D6: Continuous air-cooled load
A7: Total Combined IT Load | B7: =B5+B6 -> 8264 | C7: kW | D7: Compute + network/storage
A8: S45 Loop Supply Temperature | B8: ='Control Panel & Inputs'!$C$14 -> 45 | C8: °C | D8: Facility Water Supply (FWS)
A9: S45 Loop Return Temperature | B9: 55 | C9: °C | D9: Facility Water Return (FWR) — assumption
A10: S45 Loop Delta T | B10: =B9-B8 -> 10 | C10: °C | D10: Hydraulic temperature split
A11: S45 Liquid Flow Rate per Rack | B11: 195 | C11: LPM | D11: PG25 water/glycol mixture — vendor spec
A12: Total S45 Cluster Flow Rate | B12: =B11*'Control Panel & Inputs'!$C$10 -> 6240 | C12: LPM | D12: Primary CDU manifold demand
A13: Peak Ambient Dry-Bulb | B13: ='Control Panel & Inputs'!$C$6 -> 50 | C13: °C | D13: Abu Dhabi extreme condition
A14: S45 Peak Rejection Approach | B14: =B9-B13 -> 5 | C14: K | D14: FWR minus peak dry-bulb (positive = dry cooling viable)
A15: S45 Dry Cooler / CDU Cooling Power | B15: =B5*0.05 -> 363.2 | C15: kW | D15: 5% of liquid-cooled load — CDU pumps & EC fans (assumption)
A16: Air Loop Chiller Cooling Power | B16: =B6*0.28 -> 280 | C16: kW | D16: 28% of air-cooled load — high-ambient screw chillers (assumption)
A17: Total Cooling Peak Power | B17: =B15+B16 -> 643.2 | C17: kW | D17: Combined cooling power
A18: Peak Mechanical Load Component (MLC) | B18: =B17/B7 -> 0.077831559 | D18: Cooling power / total IT load
A19: ASHRAE 90.4 Zone 1A Limit | B19: 0.26 | D19: Maximum allowable peak MLC threshold
A20: Safety Compliance Margin | B20: =(B19-B18)/B19 -> 0.70064785 | C20: % | D20: Operational margin under the Zone 1A limit
A21: Average Utilized IT Power | B21: =B7*'Control Panel & Inputs'!$C$16*'Control Panel & Inputs'!$C$17 -> 6989.278 | C21: kW | D21: Total IT x utilization x uptime
A22: Annualized PUE | B22: ='Control Panel & Inputs'!$C$15 -> 1.08 | D22: Facility energy multiplier on IT energy
A23: Annual Facility Energy | B23: =B21*8760*B22/1000 -> 66124.161 | C23: MWh/yr | D23: Avg IT power x 8760h x PUE
A24: Annual Water Consumption | B24: =B23*'Control Panel & Inputs'!$C$9 -> 9918.6242 | C24: m³/yr | D24: Facility kWh x WUE
A25: Annual Carbon Emissions | B25: =B23*'Control Panel & Inputs'!$C$8 -> 25788.423 | C25: tCO2/yr | D25: Facility kWh x grid intensity

Sheet 5Yr Pro Forma Financials
A1: 5-Year Leveraged Financial Model & Debt Amortization
A2: UAE corporate tax (9%) with GIDLR 30%-of-EBITDA interest cap, revenue ramp & escalations, full debt schedule and equity returns
A4: Line Item (USD) | B4: Year 0 | C4: Year 1 | D4: Year 2 | E4: Year 3 | F4: Year 4 | G4: Year 5
A5: Revenue Ramp Factor | B5: 0 | C5: ='Control Panel & Inputs'!$C$34 -> 0.9 | D5: 1 | E5: 1 | F5: 1 | G5: 1
A6: Lease Revenue | B6: 0 | C6: ='Control Panel & Inputs'!$C$32*POWER(1+'Control Panel & Inputs'!$C$35,0)*C5 -> 52920000 | D6: ='Control Panel & Inputs'!$C$32*POWER(1+'Control Panel & Inputs'!$C$35,1)*D5 -> 58800000 | E6: ='Control Panel & Inputs'!$C$32*POWER(1+'Control Panel & Inputs'!$C$35,2)*E5 -> 58800000 | F6: ='Control Panel & Inputs'!$C$32*POWER(1+'Control Panel & Inputs'!$C$35,3)*F5 -> 58800000 | G6: ='Control Panel & Inputs'!$C$32*POWER(1+'Control Panel & Inputs'!$C$35,4)*G5 -> 58800000
A7: Token Revenue | B7: 0 | C7: ='Control Panel & Inputs'!$C$33*POWER((1+'Control Panel & Inputs'!$C$37)*(1-'Control Panel & Inputs'!$C$36),0)*C5 -> 22680000 | D7: ='Control Panel & Inputs'!$C$33*POWER((1+'Control Panel & Inputs'!$C$37)*(1-'Control Panel & Inputs'!$C$36),1)*D5 -> 26775000 | E7: ='Control Panel & Inputs'!$C$33*POWER((1+'Control Panel & Inputs'!$C$37)*(1-'Control Panel & Inputs'!$C$36),2)*E5 -> 28448438 | F7: ='Control Panel & Inputs'!$C$33*POWER((1+'Control Panel & Inputs'!$C$37)*(1-'Control Panel & Inputs'!$C$36),3)*F5 -> 30226465 | G7: ='Control Panel & Inputs'!$C$33*POWER((1+'Control Panel & Inputs'!$C$37)*(1-'Control Panel & Inputs'!$C$36),4)*G5 -> 32115619
A8: Gross Annual Revenue | B8: 0 | C8: =C6+C7 -> 75600000 | D8: =D6+D7 -> 85575000 | E8: =E6+E7 -> 87248438 | F8: =F6+F7 -> 89026465 | G8: =G6+G7 -> 90915619
A9: Effective Power Tariff | B9: 0 | C9: ='Control Panel & Inputs'!$C$20*POWER(1+'Control Panel & Inputs'!$C$21,0) -> 0.06 | D9: ='Control Panel & Inputs'!$C$20*POWER(1+'Control Panel & Inputs'!$C$21,1) -> 0.0612 | E9: ='Control Panel & Inputs'!$C$20*POWER(1+'Control Panel & Inputs'!$C$21,2) -> 0.062424 | F9: ='Control Panel & Inputs'!$C$20*POWER(1+'Control Panel & Inputs'!$C$21,3) -> 0.06367248 | G9: ='Control Panel & Inputs'!$C$20*POWER(1+'Control Panel & Inputs'!$C$21,4) -> 0.06494593
A10: Annual Facility Energy (kWh) | B10: 0 | C10: ='Thermal Hydraulics & MLC'!$B$23*1000 -> 66124161 | D10: ='Thermal Hydraulics & MLC'!$B$23*1000 -> 66124161 | E10: ='Thermal Hydraulics & MLC'!$B$23*1000 -> 66124161 | F10: ='Thermal Hydraulics & MLC'!$B$23*1000 -> 66124161 | G10: ='Thermal Hydraulics & MLC'!$B$23*1000 -> 66124161
A11: Electricity Cost | B11: 0 | C11: =C10*C9 -> 3967449.7 | D11: =D10*D9 -> 4046798.7 | E11: =E10*E9 -> 4127734.6 | F11: =F10*F9 -> 4210289.3 | G11: =G10*G9 -> 4294495.1
A12: Fixed Non-Power OpEx | B12: 0 | C12: ='Control Panel & Inputs'!$C$30*POWER(1+'Control Panel & Inputs'!$C$31,0) -> 10877000 | D12: ='Control Panel & Inputs'!$C$30*POWER(1+'Control Panel & Inputs'!$C$31,1) -> 11203310 | E12: ='Control Panel & Inputs'!$C$30*POWER(1+'Control Panel & Inputs'!$C$31,2) -> 11539409 | F12: ='Control Panel & Inputs'!$C$30*POWER(1+'Control Panel & Inputs'!$C$31,3) -> 11885592 | G12: ='Control Panel & Inputs'!$C$30*POWER(1+'Control Panel & Inputs'!$C$31,4) -> 12242159
A13: Total Operational Expense (OpEx) | B13: 0 | C13: =C11+C12 -> 14844450 | D13: =D11+D12 -> 15250109 | E13: =E11+E12 -> 15667144 | F13: =F11+F12 -> 16095881 | G13: =G11+G12 -> 16536654
A14: EBITDA | B14: 0 | C14: =C8-C13 -> 60755550 | D14: =D8-D13 -> 70324891 | E14: =E8-E13 -> 71581294 | F14: =F8-F13 -> 72930584 | G14: =G8-G13 -> 74378964
A15: EBITDA Margin | B15: 0 | C15: =C14/C8 -> 0.80364485 | D15: =D14/D8 -> 0.82179248 | E15: =E14/E8 -> 0.82043066 | F15: =F14/F8 -> 0.81920117 | G15: =G14/G8 -> 0.81810986
A16: CapEx Initial Outlay | B16: ='Control Panel & Inputs'!$C$22 -> 139500000 | C16: 0 | D16: 0 | E16: 0 | F16: 0 | G16: 0
A17: Debt Financed Amount | B17: =B16*'Control Panel & Inputs'!$C$24 -> 111600000 | C17: 0 | D17: 0 | E17: 0 | F17: 0 | G17: 0
A18: Equity Outlay | B18: =B16-B17 -> 27900000 | C18: 0 | D18: 0 | E18: 0 | F18: 0 | G18: 0
A19: Beginning Debt Balance | B19: 0 | C19: =B17 -> 111600000 | D19: =C23 -> 91999186 | E19: =D23 -> 71124318 | F19: =E23 -> 48892585 | G19: =F23 -> 25215788
A20: Annual Debt Service (P+I) | B20: 0 | C20: =-PMT('Control Panel & Inputs'!$C$25,'Control Panel & Inputs'!$C$26,B17) -> 26854814 | D20: =-PMT('Control Panel & Inputs'!$C$25,'Control Panel & Inputs'!$C$26,B17) -> 26854814 | E20: =-PMT('Control Panel & Inputs'!$C$25,'Control Panel & Inputs'!$C$26,B17) -> 26854814 | F20: =-PMT('Control Panel & Inputs'!$C$25,'Control Panel & Inputs'!$C$26,B17) -> 26854814 | G20: =-PMT('Control Panel & Inputs'!$C$25,'Control Panel & Inputs'!$C$26,B17) -> 26854814
A21: Interest Expense | B21: 0 | C21: =C19*'Control Panel & Inputs'!$C$25 -> 7254000 | D21: =D19*'Control Panel & Inputs'!$C$25 -> 5979947.1 | E21: =E19*'Control Panel & Inputs'!$C$25 -> 4623080.7 | F21: =F19*'Control Panel & Inputs'!$C$25 -> 3178018 | G21: =G19*'Control Panel & Inputs'!$C$25 -> 1639026.2
A22: Debt Principal Payment | B22: 0 | C22: =C20-C21 -> 19600814 | D22: =D20-D21 -> 20874867 | E22: =E20-E21 -> 22231734 | F22: =F20-F21 -> 23676796 | G22: =G20-G21 -> 25215788
A23: Ending Debt Balance | B23: 0 | C23: =C19-C22 -> 91999186 | D23: =D19-D22 -> 71124318 | E23: =E19-E22 -> 48892585 | F23: =F19-F22 -> 25215788 | G23: =G19-G22 -> 0
A24: Depreciation (5-Yr Straight Line) | B24: 0 | C24: =B16/5 -> 27900000 | D24: =B16/5 -> 27900000 | E24: =B16/5 -> 27900000 | F24: =B16/5 -> 27900000 | G24: =B16/5 -> 27900000
A25: GIDLR Deductible Interest | B25: 0 | C25: =MIN(C21,'Control Panel & Inputs'!$C$28*C14) -> 7254000 | D25: =MIN(D21,'Control Panel & Inputs'!$C$28*D14) -> 5979947.1 | E25: =MIN(E21,'Control Panel & Inputs'!$C$28*E14) -> 4623080.7 | F25: =MIN(F21,'Control Panel & Inputs'!$C$28*F14) -> 3178018 | G25: =MIN(G21,'Control Panel & Inputs'!$C$28*G14) -> 1639026.2
A26: Taxable Income | B26: 0 | C26: =C14-C24-C25 -> 25601550 | D26: =D14-D24-D25 -> 36444944 | E26: =E14-E24-E25 -> 39058213 | F26: =F14-F24-F25 -> 41852566 | G26: =G14-G24-G25 -> 44839938
A27: UAE Corporate Tax | B27: 0 | C27: =MAX(0,C26)*'Control Panel & Inputs'!$C$27 -> 2304139.5 | D27: =MAX(0,D26)*'Control Panel & Inputs'!$C$27 -> 3280045 | E27: =MAX(0,E26)*'Control Panel & Inputs'!$C$27 -> 3515239.2 | F27: =MAX(0,F26)*'Control Panel & Inputs'!$C$27 -> 3766730.9 | G27: =MAX(0,G26)*'Control Panel & Inputs'!$C$27 -> 4035594.4
A28: Residual Value Recovery | B28: 0 | C28: 0 | D28: 0 | E28: 0 | F28: 0 | G28: ='Control Panel & Inputs'!$C$22*'Control Panel & Inputs'!$C$23 -> 13950000
A29: Leveraged Free Cash Flow (FCFE) | B29: =-B18 -> -27900000 | C29: =C14-C20-C27+C28 -> 31596596 | D29: =D14-D20-D27+D28 -> 40190032 | E29: =E14-E20-E27+E28 -> 41211240 | F29: =F14-F20-F27+F28 -> 42309039 | G29: =G14-G20-G27+G28 -> 57438556
A30: Cumulative FCFE | B30: =B29 -> -27900000 | C30: =B30+C29 -> 3696596.4 | D30: =C30+D29 -> 43886628 | E30: =D30+E29 -> 85097868 | F30: =E30+F29 -> 1.2740691e+08 | G30: =F30+G29 -> 1.8484546e+08
A31: Debt Service Coverage Ratio (DSCR) | B31: 0 | C31: =C14/C20 -> 2.2623709 | D31: =D14/D20 -> 2.618707 | E31: =E14/E20 -> 2.665492 | F31: =F14/F20 -> 2.7157359 | G31: =G14/G20 -> 2.7696697
A32: Unlevered Tax (no interest shield) | B32: 0 | C32: =MAX(0,C14-C24)*'Control Panel & Inputs'!$C$27 -> 2956999.5 | D32: =MAX(0,D14-D24)*'Control Panel & Inputs'!$C$27 -> 3818240.2 | E32: =MAX(0,E14-E24)*'Control Panel & Inputs'!$C$27 -> 3931316.4 | F32: =MAX(0,F14-F24)*'Control Panel & Inputs'!$C$27 -> 4052752.6 | G32: =MAX(0,G14-G24)*'Control Panel & Inputs'!$C$27 -> 4183106.8
A33: Unlevered Free Cash Flow (FCFF) | B33: =-B16 -> -139500000 | C33: =C14-C32+C28 -> 57798551 | D33: =D14-D32+D28 -> 66506651 | E33: =E14-E32+E28 -> 67649977 | F33: =F14-F32+F28 -> 68877831 | G33: =G14-G32+G28 -> 84145858
A35: Equity Returns Summary
A36: Equity IRR (5-Yr, levered) | B36: =IRR(B29:G29) -> 1.2650683
A37: Project IRR (5-Yr, unlevered) | B37: =IRR(B33:G33) -> 0.3754892
A38: Equity NPV @ hurdle rate | B38: =B29+NPV('Control Panel & Inputs'!$C$29,C29:G29) -> 1.0980924e+08
A39: MOIC (total distributions / equity) | B39: =SUM(C29:G29)/-B29 -> 7.6252854
A40: Payback Period | B40: =IFERROR(COUNTIF(B30:G30,"<0")-1+ABS(INDEX(B30:G30,COUNTIF(B30:G30,"<0")))/INDEX(B29:G29,COUNTIF(B30:G30,"<0")+1),">5 yrs") -> 0.8830065
A41: Minimum DSCR | B41: =MIN(C31:G31) -> 2.2623709
A42: Average DSCR | B42: =AVERAGE(C31:G31) -> 2.6063951

Sheet Unit Economics & KPIs
A1: Unit Economics & Operational KPIs
A2: GPU-hour and token-level economics (steady-state Year 2, post-ramp) — all cells formula-driven
A4: KPI | B4: Value | C4: Unit | D4: Derivation
A5: Total GPU Count | B5: ='Control Panel & Inputs'!$C$10*'Control Panel & Inputs'!$C$11 -> 2304 | C5: GPUs | D5: Racks x GPUs per rack
A6: Available GPU-hours / yr | B6: =B5*8760*'Control Panel & Inputs'!$C$17 -> 20082125 | C6: GPU-hrs | D6: GPUs x 8760h x uptime
A7: Sold GPU-hours / yr | B7: =B6*'Control Panel & Inputs'!$C$16 -> 17069806 | C7: GPU-hrs | D7: Available x utilization
A8: Blended Revenue per Sold GPU-hour | B8: ='5Yr Pro Forma Financials'!D$8/B7 -> 5.013238 | C8: $/GPU-hr | D8: Year 2 gross revenue / sold GPU-hours
A9: Cash OpEx per Sold GPU-hour | B9: ='5Yr Pro Forma Financials'!D$13/B7 -> 0.89339671 | C9: $/GPU-hr | D9: Year 2 total OpEx / sold GPU-hours
A10: EBITDA per Sold GPU-hour | B10: =B8-B9 -> 4.1198413 | C10: $/GPU-hr | D10: Revenue minus cash OpEx per GPU-hour
A11: CapEx per GPU | B11: ='Control Panel & Inputs'!$C$22/B5 -> 60546.875 | C11: $/GPU | D11: Total CapEx / GPU count
A12: CapEx per MW of IT Load | B12: ='Control Panel & Inputs'!$C$22/('Thermal Hydraulics & MLC'!$B$7/1000) -> 16880445 | C12: $/MW | D12: Total CapEx / total IT MW
A13: Revenue per MW of IT Load | B13: ='5Yr Pro Forma Financials'!D$8/('Thermal Hydraulics & MLC'!$B$7/1000) -> 10355155 | C13: $/MW/yr | D13: Year 2 revenue / total IT MW
A14: Annual Token Capacity (token fleet) | B14: =B5*'Control Panel & Inputs'!$C$19*'Control Panel & Inputs'!$C$18*3600*8760*'Control Panel & Inputs'!$C$16*'Control Panel & Inputs'!$C$17/1000000000000 -> 33.183703 | C14: T tokens/yr | D14: Token-fleet GPUs x tok/s x seconds x utilization x uptime
A15: Implied Realized Price per M Tokens | B15: ='5Yr Pro Forma Financials'!D$7/(B14*1000000) -> 0.80687198 | C15: $/M tok | D15: Year 2 token revenue / token capacity
A16: Cash Cost per M Tokens | B16: ='5Yr Pro Forma Financials'!D$13*'Control Panel & Inputs'!$C$19/(B14*1000000) -> 0.13786986 | C16: $/M tok | D16: Token-fleet share of Year 2 OpEx / token capacity
A17: Energy Cost as % of Revenue | B17: ='5Yr Pro Forma Financials'!D$11/'5Yr Pro Forma Financials'!D$8 -> 0.047289497 | C17: % | D17: Year 2 electricity / Year 2 revenue
A18: Breakeven Power Tariff (EBITDA = 0) | B18: =('5Yr Pro Forma Financials'!D$8-'5Yr Pro Forma Financials'!D$12)/'5Yr Pro Forma Financials'!D$10 -> 1.1247279 | C18: $/kWh | D18: (Year 2 revenue - fixed OpEx) / annual kWh
A19: Min Revenue for 1.00x DSCR | B19: ='5Yr Pro Forma Financials'!D$20+'5Yr Pro Forma Financials'!D$13 -> 42104923 | C19: USD/yr | D19: Debt service + Year 2 OpEx
A20: Revenue Headroom above 1.00x DSCR | B20: =1-B19/'5Yr Pro Forma Financials'!D$8 -> 0.50797636 | C20: % | D20: 1 - min revenue / Year 2 revenue

Sheet Sensitivity Engine
A1: Sensitivity Engine — 16 Live Scenarios
A2: Each row re-runs the full leveraged model (debt schedule, GIDLR tax cap, residual value) for one tariff x debt-ratio combination
A4: Scenario | B4: Tariff $/kWh | C4: Debt % | D4: Debt $ | E4: Equity $ | F4: Debt Service | G4: Y0 FCFE | H4: Y1 FCFE | I4: Y2 FCFE | J4: Y3 FCFE | K4: Y4 FCFE | L4: Y5 FCFE | M4: Equity IRR | N4: Avg DSCR
A5: $0.04/kWh @ 50% debt | B5: 0.04 | C5: 0.5 | D5: ='Control Panel & Inputs'!$C$22*$C5 -> 69750000 | E5: ='Control Panel & Inputs'!$C$22-$D5 -> 69750000 | F5: =-PMT('Control Panel & Inputs'!$C$25,'Control Panel & Inputs'!$C$26,$D5) -> 16784259 | G5: =-$E5 -> -69750000 | H5: =B23-$F5-MAX(0,B23-'Control Panel & Inputs'!$C$22/5-MIN(-IPMT('Control Panel & Inputs'!$C$25,1,'Control Panel & Inputs'!$C$26,$D5),'Control Panel & Inputs'!$C$28*B23))*'Control Panel & Inputs'!$C$27 -> 42625789 | I5: =C23-$F5-MAX(0,C23-'Control Panel & Inputs'!$C$22/5-MIN(-IPMT('Control Panel & Inputs'!$C$25,2,'Control Panel & Inputs'!$C$26,$D5),'Control Panel & Inputs'!$C$28*C23))*'Control Panel & Inputs'!$C$27 -> 51286293 | J5: =D23-$F5-MAX(0,D23-'Control Panel & Inputs'!$C$22/5-MIN(-IPMT('Control Panel & Inputs'!$C$25,3,'Control Panel & Inputs'!$C$26,$D5),'Control Panel & Inputs'!$C$28*D23))*'Control Panel & Inputs'!$C$27 -> 52377846 | K5: =E23-$F5-MAX(0,E23-'Control Panel & Inputs'!$C$22/5-MIN(-IPMT('Control Panel & Inputs'!$C$25,4,'Control Panel & Inputs'!$C$26,$D5),'Control Panel & Inputs'!$C$28*E23))*'Control Panel & Inputs'!$C$27 -> 53549457 | L5: =F23-$F5-MAX(0,F23-'Control Panel & Inputs'!$C$22/5-MIN(-IPMT('Control Panel & Inputs'!$C$25,5,'Control Panel & Inputs'!$C$26,$D5),'Control Panel & Inputs'!$C$28*F23))*'Control Panel & Inputs'!$C$27+'Control Panel & Inputs'!$C$22*'Control Panel & Inputs'!$C$23 -> 68756457 | M5: =IRR(G5:L5) -> 0.64397875 | N5: =AVERAGE(B23:F23)/$F5 -> 4.2522406
A6: $0.04/kWh @ 60% debt | B6: 0.04 | C6: 0.6 | D6: ='Control Panel & Inputs'!$C$22*$C6 -> 83700000 | E6: ='Control Panel & Inputs'!$C$22-$D6 -> 55800000 | F6: =-PMT('Control Panel & Inputs'!$C$25,'Control Panel & Inputs'!$C$26,$D6) -> 20141111 | G6: =-$E6 -> -55800000 | H6: =B24-$F6-MAX(0,B24-'Control Panel & Inputs'!$C$22/5-MIN(-IPMT('Control Panel & Inputs'!$C$25,1,'Control Panel & Inputs'!$C$26,$D6),'Control Panel & Inputs'!$C$28*B24))*'Control Panel & Inputs'!$C$27 -> 39350545 | I6: =C24-$F6-MAX(0,C24-'Control Panel & Inputs'!$C$22/5-MIN(-IPMT('Control Panel & Inputs'!$C$25,2,'Control Panel & Inputs'!$C$26,$D6),'Control Panel & Inputs'!$C$28*C24))*'Control Panel & Inputs'!$C$27 -> 47996716 | J6: =D24-$F6-MAX(0,D24-'Control Panel & Inputs'!$C$22/5-MIN(-IPMT('Control Panel & Inputs'!$C$25,3,'Control Panel & Inputs'!$C$26,$D6),'Control Panel & Inputs'!$C$28*D24))*'Control Panel & Inputs'!$C$27 -> 49073004 | K6: =E24-$F6-MAX(0,E24-'Control Panel & Inputs'!$C$22/5-MIN(-IPMT('Control Panel & Inputs'!$C$25,4,'Control Panel & Inputs'!$C$26,$D6),'Control Panel & Inputs'!$C$28*E24))*'Control Panel & Inputs'!$C$27 -> 50228358 | L6: =F24-$F6-MAX(0,F24-'Control Panel & Inputs'!$C$22/5-MIN(-IPMT('Control Panel & Inputs'!$C$25,5,'Control Panel & Inputs'!$C$26,$D6),'Control Panel & Inputs'!$C$28*F24))*'Control Panel & Inputs'!$C$27+'Control Panel & Inputs'!$C$22*'Control Panel & Inputs'!$C$23 -> 65418045 | M6: =IRR(G6:L6) -> 0.76238252 | N6: =AVERAGE(B24:F24)/$F6 -> 3.5435338
A7: $0.04/kWh @ 70% debt | B7: 0.04 | C7: 0.7 | D7: ='Control Panel & Inputs'!$C$22*$C7 -> 97650000 | E7: ='Control Panel & Inputs'!$C$22-$D7 -> 41850000 | F7: =-PMT('Control Panel & Inputs'!$C$25,'Control Panel & Inputs'!$C$26,$D7) -> 23497963 | G7: =-$E7 -> -41850000 | H7: =B25-$F7-MAX(0,B25-'Control Panel & Inputs'!$C$22/5-MIN(-IPMT('Control Panel & Inputs'!$C$25,1,'Control Panel & Inputs'!$C$26,$D7),'Control Panel & Inputs'!$C$28*B25))*'Control Panel & Inputs'!$C$27 -> 36075300 | I7: =C25-$F7-MAX(0,C25-'Control Panel & Inputs'!$C$22/5-MIN(-IPMT('Control Panel & Inputs'!$C$25,2,'Control Panel & Inputs'!$C$26,$D7),'Control Panel & Inputs'!$C$28*C25))*'Control Panel & Inputs'!$C$27 -> 44707138 | J7: =D25-$F7-MAX(0,D25-'Control Panel & Inputs'!$C$22/5-MIN(-IPMT('Control Panel & Inputs'!$C$25,3,'Control Panel & Inputs'!$C$26,$D7),'Control Panel & Inputs'!$C$28*D25))*'Control Panel & Inputs'!$C$27 -> 45768162 | K7: =E25-$F7-MAX(0,E25-'Control Panel & Inputs'!$C$22/5-MIN(-IPMT('Control Panel & Inputs'!$C$25,4,'Control Panel & Inputs'!$C$26,$D7),'Control Panel & Inputs'!$C$28*E25))*'Control Panel & Inputs'!$C$27 -> 46907259 | L7: =F25-$F7-MAX(0,F25-'Control Panel & Inputs'!$C$22/5-MIN(-IPMT('Control Panel & Inputs'!$C$25,5,'Control Panel & Inputs'!$C$26,$D7),'Control Panel & Inputs'!$C$28*F25))*'Control Panel & Inputs'!$C$27+'Control Panel & Inputs'!$C$22*'Control Panel & Inputs'!$C$23 -> 62079632 | M7: =IRR(G7:L7) -> 0.95059746 | N7: =AVERAGE(B25:F25)/$F7 -> 3.0373147
A8: $0.04/kWh @ 80% debt | B8: 0.04 | C8: 0.8 | D8: ='Control Panel & Inputs'!$C$22*$C8 -> 111600000 | E8: ='Control Panel & Inputs'!$C$22-$D8 -> 27900000 | F8: =-PMT('Control Panel & Inputs'!$C$25,'Control Panel & Inputs'!$C$26,$D8) -> 26854814 | G8: =-$E8 -> -27900000 | H8: =B26-$F8-MAX(0,B26-'Control Panel & Inputs'!$C$22/5-MIN(-IPMT('Control Panel & Inputs'!$C$25,1,'Control Panel & Inputs'!$C$26,$D8),'Control Panel & Inputs'!$C$28*B26))*'Control Panel & Inputs'!$C$27 -> 32800056 | I8: =C26-$F8-MAX(0,C26-'Control Panel & Inputs'!$C$22/5-MIN(-IPMT('Control Panel & Inputs'!$C$25,2,'Control Panel & Inputs'!$C$26,$D8),'Control Panel & Inputs'!$C$28*C26))*'Control Panel & Inputs'!$C$27 -> 41417561 | J8: =D26-$F8-MAX(0,D26-'Control Panel & Inputs'!$C$22/5-MIN(-IPMT('Control Panel & Inputs'!$C$25,3,'Control Panel & Inputs'!$C$26,$D8),'Control Panel & Inputs'!$C$28*D26))*'Control Panel & Inputs'!$C$27 -> 42463320 | K8: =E26-$F8-MAX(0,E26-'Control Panel & Inputs'!$C$22/5-MIN(-IPMT('Control Panel & Inputs'!$C$25,4,'Control Panel & Inputs'!$C$26,$D8),'Control Panel & Inputs'!$C$28*E26))*'Control Panel & Inputs'!$C$27 -> 43586160 | L8: =F26-$F8-MAX(0,F26-'Control Panel & Inputs'!$C$22/5-MIN(-IPMT('Control Panel & Inputs'!$C$25,5,'Control Panel & Inputs'!$C$26,$D8),'Control Panel & Inputs'!$C$28*F26))*'Control Panel & Inputs'!$C$27+'Control Panel & Inputs'!$C$22*'Control Panel & Inputs'!$C$23 -> 58741219 | M8: =IRR(G8:L8) -> 1.3067984 | N8: =AVERAGE(B26:F26)/$F8 -> 2.6576504
A9: $0.06/kWh @ 50% debt | B9: 0.06 | C9: 0.5 | D9: ='Control Panel & Inputs'!$C$22*$C9 -> 69750000 | E9: ='Control Panel & Inputs'!$C$22-$D9 -> 69750000 | F9: =-PMT('Control Panel & Inputs'!$C$25,'Control Panel & Inputs'!$C$26,$D9) -> 16784259 | G9: =-$E9 -> -69750000 | H9: =B27-$F9-MAX(0,B27-'Control Panel & Inputs'!$C$22/5-MIN(-IPMT('Control Panel & Inputs'!$C$25,1,'Control Panel & Inputs'!$C$26,$D9),'Control Panel & Inputs'!$C$28*B27))*'Control Panel & Inputs'!$C$27 -> 41422329 | I9: =C27-$F9-MAX(0,C27-'Control Panel & Inputs'!$C$22/5-MIN(-IPMT('Control Panel & Inputs'!$C$25,2,'Control Panel & Inputs'!$C$26,$D9),'Control Panel & Inputs'!$C$28*C27))*'Control Panel & Inputs'!$C$27 -> 50058764 | J9: =D27-$F9-MAX(0,D27-'Control Panel & Inputs'!$C$22/5-MIN(-IPMT('Control Panel & Inputs'!$C$25,3,'Control Panel & Inputs'!$C$26,$D9),'Control Panel & Inputs'!$C$28*D27))*'Control Panel & Inputs'!$C$27 -> 51125766 | K9: =E27-$F9-MAX(0,E27-'Control Panel & Inputs'!$C$22/5-MIN(-IPMT('Control Panel & Inputs'!$C$25,4,'Control Panel & Inputs'!$C$26,$D9),'Control Panel & Inputs'!$C$28*E27))*'Control Panel & Inputs'!$C$27 -> 52272336 | L9: =F27-$F9-MAX(0,F27-'Control Panel & Inputs'!$C$22/5-MIN(-IPMT('Control Panel & Inputs'!$C$25,5,'Control Panel & Inputs'!$C$26,$D9),'Control Panel & Inputs'!$C$28*F27))*'Control Panel & Inputs'!$C$27+'Control Panel & Inputs'!$C$22*'Control Panel & Inputs'!$C$23 -> 67453794 | M9: =IRR(G9:L9) -> 0.62563439 | N9: =AVERAGE(B27:F27)/$F9 -> 4.1702322
A10: $0.06/kWh @ 60% debt | B10: 0.06 | C10: 0.6 | D10: ='Control Panel & Inputs'!$C$22*$C10 -> 83700000 | E10: ='Control Panel & Inputs'!$C$22-$D10 -> 55800000 | F10: =-PMT('Control Panel & Inputs'!$C$25,'Control Panel & Inputs'!$C$26,$D10) -> 20141111 | G10: =-$E10 -> -55800000 | H10: =B28-$F10-MAX(0,B28-'Control Panel & Inputs'!$C$22/5-MIN(-IPMT('Control Panel & Inputs'!$C$25,1,'Control Panel & Inputs'!$C$26,$D10),'Control Panel & Inputs'!$C$28*B28))*'Control Panel & Inputs'!$C$27 -> 38147085 | I10: =C28-$F10-MAX(0,C28-'Control Panel & Inputs'!$C$22/5-MIN(-IPMT('Control Panel & Inputs'!$C$25,2,'Control Panel & Inputs'!$C$26,$D10),'Control Panel & Inputs'!$C$28*C28))*'Control Panel & Inputs'!$C$27 -> 46769187 | J10: =D28-$F10-MAX(0,D28-'Control Panel & Inputs'!$C$22/5-MIN(-IPMT('Control Panel & Inputs'!$C$25,3,'Control Panel & Inputs'!$C$26,$D10),'Control Panel & Inputs'!$C$28*D28))*'Control Panel & Inputs'!$C$27 -> 47820924 | K10: =E28-$F10-MAX(0,E28-'Control Panel & Inputs'!$C$22/5-MIN(-IPMT('Control Panel & Inputs'!$C$25,4,'Control Panel & Inputs'!$C$26,$D10),'Control Panel & Inputs'!$C$28*E28))*'Control Panel & Inputs'!$C$27 -> 48951237 | L10: =F28-$F10-MAX(0,F28-'Control Panel & Inputs'!$C$22/5-MIN(-IPMT('Control Panel & Inputs'!$C$25,5,'Control Panel & Inputs'!$C$26,$D10),'Control Panel & Inputs'!$C$28*F28))*'Control Panel & Inputs'!$C$27+'Control Panel & Inputs'!$C$22*'Control Panel & Inputs'!$C$23 -> 64115381 | M10: =IRR(G10:L10) -> 0.74012926 | N10: =AVERAGE(B28:F28)/$F10 -> 3.4751935
A11: $0.06/kWh @ 70% debt | B11: 0.06 | C11: 0.7 | D11: ='Control Panel & Inputs'!$C$22*$C11 -> 97650000 | E11: ='Control Panel & Inputs'!$C$22-$D11 -> 41850000 | F11: =-PMT('Control Panel & Inputs'!$C$25,'Control Panel & Inputs'!$C$26,$D11) -> 23497963 | G11: =-$E11 -> -41850000 | H11: =B29-$F11-MAX(0,B29-'Control Panel & Inputs'!$C$22/5-MIN(-IPMT('Control Panel & Inputs'!$C$25,1,'Control Panel & Inputs'!$C$26,$D11),'Control Panel & Inputs'!$C$28*B29))*'Control Panel & Inputs'!$C$27 -> 34871841 | I11: =C29-$F11-MAX(0,C29-'Control Panel & Inputs'!$C$22/5-MIN(-IPMT('Control Panel & Inputs'!$C$25,2,'Control Panel & Inputs'!$C$26,$D11),'Control Panel & Inputs'!$C$28*C29))*'Control Panel & Inputs'!$C$27 -> 43479609 | J11: =D29-$F11-MAX(0,D29-'Control Panel & Inputs'!$C$22/5-MIN(-IPMT('Control Panel & Inputs'!$C$25,3,'Control Panel & Inputs'!$C$26,$D11),'Control Panel & Inputs'!$C$28*D29))*'Control Panel & Inputs'!$C$27 -> 44516082 | K11: =E29-$F11-MAX(0,E29-'Control Panel & Inputs'!$C$22/5-MIN(-IPMT('Control Panel & Inputs'!$C$25,4,'Control Panel & Inputs'!$C$26,$D11),'Control Panel & Inputs'!$C$28*E29))*'Control Panel & Inputs'!$C$27 -> 45630138 | L11: =F29-$F11-MAX(0,F29-'Control Panel & Inputs'!$C$22/5-MIN(-IPMT('Control Panel & Inputs'!$C$25,5,'Control Panel & Inputs'!$C$26,$D11),'Control Panel & Inputs'!$C$28*F29))*'Control Panel & Inputs'!$C$27+'Control Panel & Inputs'!$C$22*'Control Panel & Inputs'!$C$23 -> 60776968 | M11: =IRR(G11:L11) -> 0.92187536 | N11: =AVERAGE(B29:F29)/$F11 -> 2.9787373
A12: $0.06/kWh @ 80% debt | B12: 0.06 | C12: 0.8 | D12: ='Control Panel & Inputs'!$C$22*$C12 -> 111600000 | E12: ='Control Panel & Inputs'!$C$22-$D12 -> 27900000 | F12: =-PMT('Control Panel & Inputs'!$C$25,'Control Panel & Inputs'!$C$26,$D12) -> 26854814 | G12: =-$E12 -> -27900000 | H12: =B30-$F12-MAX(0,B30-'Control Panel & Inputs'!$C$22/5-MIN(-IPMT('Control Panel & Inputs'!$C$25,1,'Control Panel & Inputs'!$C$26,$D12),'Control Panel & Inputs'!$C$28*B30))*'Control Panel & Inputs'!$C$27 -> 31596596 | I12: =C30-$F12-MAX(0,C30-'Control Panel & Inputs'!$C$22/5-MIN(-IPMT('Control Panel & Inputs'!$C$25,2,'Control Panel & Inputs'!$C$26,$D12),'Control Panel & Inputs'!$C$28*C30))*'Control Panel & Inputs'!$C$27 -> 40190032 | J12: =D30-$F12-MAX(0,D30-'Control Panel & Inputs'!$C$22/5-MIN(-IPMT('Control Panel & Inputs'!$C$25,3,'Control Panel & Inputs'!$C$26,$D12),'Control Panel & Inputs'!$C$28*D30))*'Control Panel & Inputs'!$C$27 -> 41211240 | K12: =E30-$F12-MAX(0,E30-'Control Panel & Inputs'!$C$22/5-MIN(-IPMT('Control Panel & Inputs'!$C$25,4,'Control Panel & Inputs'!$C$26,$D12),'Control Panel & Inputs'!$C$28*E30))*'Control Panel & Inputs'!$C$27 -> 42309039 | L12: =F30-$F12-MAX(0,F30-'Control Panel & Inputs'!$C$22/5-MIN(-IPMT('Control Panel & Inputs'!$C$25,5,'Control Panel & Inputs'!$C$26,$D12),'Control Panel & Inputs'!$C$28*F30))*'Control Panel & Inputs'!$C$27+'Control Panel & Inputs'!$C$22*'Control Panel & Inputs'!$C$23 -> 57438556 | M12: =IRR(G12:L12) -> 1.2650683 | N12: =AVERAGE(B30:F30)/$F12 -> 2.6063951
A13: $0.08/kWh @ 50% debt | B13: 0.08 | C13: 0.5 | D13: ='Control Panel & Inputs'!$C$22*$C13 -> 69750000 | E13: ='Control Panel & Inputs'!$C$22-$D13 -> 69750000 | F13: =-PMT('Control Panel & Inputs'!$C$25,'Control Panel & Inputs'!$C$26,$D13) -> 16784259 | G13: =-$E13 -> -69750000 | H13: =B31-$F13-MAX(0,B31-'Control Panel & Inputs'!$C$22/5-MIN(-IPMT('Control Panel & Inputs'!$C$25,1,'Control Panel & Inputs'!$C$26,$D13),'Control Panel & Inputs'!$C$28*B31))*'Control Panel & Inputs'!$C$27 -> 40218870 | I13: =C31-$F13-MAX(0,C31-'Control Panel & Inputs'!$C$22/5-MIN(-IPMT('Control Panel & Inputs'!$C$25,2,'Control Panel & Inputs'!$C$26,$D13),'Control Panel & Inputs'!$C$28*C31))*'Control Panel & Inputs'!$C$27 -> 48831235 | J13: =D31-$F13-MAX(0,D31-'Control Panel & Inputs'!$C$22/5-MIN(-IPMT('Control Panel & Inputs'!$C$25,3,'Control Panel & Inputs'!$C$26,$D13),'Control Panel & Inputs'!$C$28*D31))*'Control Panel & Inputs'!$C$27 -> 49873687 | K13: =E31-$F13-MAX(0,E31-'Control Panel & Inputs'!$C$22/5-MIN(-IPMT('Control Panel & Inputs'!$C$25,4,'Control Panel & Inputs'!$C$26,$D13),'Control Panel & Inputs'!$C$28*E31))*'Control Panel & Inputs'!$C$27 -> 50995215 | L13: =F31-$F13-MAX(0,F31-'Control Panel & Inputs'!$C$22/5-MIN(-IPMT('Control Panel & Inputs'!$C$25,5,'Control Panel & Inputs'!$C$26,$D13),'Control Panel & Inputs'!$C$28*F31))*'Control Panel & Inputs'!$C$27+'Control Panel & Inputs'!$C$22*'Control Panel & Inputs'!$C$23 -> 66151130 | M13: =IRR(G13:L13) -> 0.60723023 | N13: =AVERAGE(B31:F31)/$F13 -> 4.0882237
A14: $0.08/kWh @ 60% debt | B14: 0.08 | C14: 0.6 | D14: ='Control Panel & Inputs'!$C$22*$C14 -> 83700000 | E14: ='Control Panel & Inputs'!$C$22-$D14 -> 55800000 | F14: =-PMT('Control Panel & Inputs'!$C$25,'Control Panel & Inputs'!$C$26,$D14) -> 20141111 | G14: =-$E14 -> -55800000 | H14: =B32-$F14-MAX(0,B32-'Control Panel & Inputs'!$C$22/5-MIN(-IPMT('Control Panel & Inputs'!$C$25,1,'Control Panel & Inputs'!$C$26,$D14),'Control Panel & Inputs'!$C$28*B32))*'Control Panel & Inputs'!$C$27 -> 36943625 | I14: =C32-$F14-MAX(0,C32-'Control Panel & Inputs'!$C$22/5-MIN(-IPMT('Control Panel & Inputs'!$C$25,2,'Control Panel & Inputs'!$C$26,$D14),'Control Panel & Inputs'!$C$28*C32))*'Control Panel & Inputs'!$C$27 -> 45541658 | J14: =D32-$F14-MAX(0,D32-'Control Panel & Inputs'!$C$22/5-MIN(-IPMT('Control Panel & Inputs'!$C$25,3,'Control Panel & Inputs'!$C$26,$D14),'Control Panel & Inputs'!$C$28*D32))*'Control Panel & Inputs'!$C$27 -> 46568845 | K14: =E32-$F14-MAX(0,E32-'Control Panel & Inputs'!$C$22/5-MIN(-IPMT('Control Panel & Inputs'!$C$25,4,'Control Panel & Inputs'!$C$26,$D14),'Control Panel & Inputs'!$C$28*E32))*'Control Panel & Inputs'!$C$27 -> 47674116 | L14: =F32-$F14-MAX(0,F32-'Control Panel & Inputs'!$C$22/5-MIN(-IPMT('Control Panel & Inputs'!$C$25,5,'Control Panel & Inputs'!$C$26,$D14),'Control Panel & Inputs'!$C$28*F32))*'Control Panel & Inputs'!$C$27+'Control Panel & Inputs'!$C$22*'Control Panel & Inputs'!$C$23 -> 62812718 | M14: =IRR(G14:L14) -> 0.71781947 | N14: =AVERAGE(B32:F32)/$F14 -> 3.4068531
A15: $0.08/kWh @ 70% debt | B15: 0.08 | C15: 0.7 | D15: ='Control Panel & Inputs'!$C$22*$C15 -> 97650000 | E15: ='Control Panel & Inputs'!$C$22-$D15 -> 41850000 | F15: =-PMT('Control Panel & Inputs'!$C$25,'Control Panel & Inputs'!$C$26,$D15) -> 23497963 | G15: =-$E15 -> -41850000 | H15: =B33-$F15-MAX(0,B33-'Control Panel & Inputs'!$C$22/5-MIN(-IPMT('Control Panel & Inputs'!$C$25,1,'Control Panel & Inputs'!$C$26,$D15),'Control Panel & Inputs'!$C$28*B33))*'Control Panel & Inputs'!$C$27 -> 33668381 | I15: =C33-$F15-MAX(0,C33-'Control Panel & Inputs'!$C$22/5-MIN(-IPMT('Control Panel & Inputs'!$C$25,2,'Control Panel & Inputs'!$C$26,$D15),'Control Panel & Inputs'!$C$28*C33))*'Control Panel & Inputs'!$C$27 -> 42252080 | J15: =D33-$F15-MAX(0,D33-'Control Panel & Inputs'!$C$22/5-MIN(-IPMT('Control Panel & Inputs'!$C$25,3,'Control Panel & Inputs'!$C$26,$D15),'Control Panel & Inputs'!$C$28*D33))*'Control Panel & Inputs'!$C$27 -> 43264003 | K15: =E33-$F15-MAX(0,E33-'Control Panel & Inputs'!$C$22/5-MIN(-IPMT('Control Panel & Inputs'!$C$25,4,'Control Panel & Inputs'!$C$26,$D15),'Control Panel & Inputs'!$C$28*E33))*'Control Panel & Inputs'!$C$27 -> 44353017 | L15: =F33-$F15-MAX(0,F33-'Control Panel & Inputs'!$C$22/5-MIN(-IPMT('Control Panel & Inputs'!$C$25,5,'Control Panel & Inputs'!$C$26,$D15),'Control Panel & Inputs'!$C$28*F33))*'Control Panel & Inputs'!$C$27+'Control Panel & Inputs'!$C$22*'Control Panel & Inputs'!$C$23 -> 59474305 | M15: =IRR(G15:L15) -> 0.89311254 | N15: =AVERAGE(B33:F33)/$F15 -> 2.9201598
A16: $0.08/kWh @ 80% debt | B16: 0.08 | C16: 0.8 | D16: ='Control Panel & Inputs'!$C$22*$C16 -> 111600000 | E16: ='Control Panel & Inputs'!$C$22-$D16 -> 27900000 | F16: =-PMT('Control Panel & Inputs'!$C$25,'Control Panel & Inputs'!$C$26,$D16) -> 26854814 | G16: =-$E16 -> -27900000 | H16: =B34-$F16-MAX(0,B34-'Control Panel & Inputs'!$C$22/5-MIN(-IPMT('Control Panel & Inputs'!$C$25,1,'Control Panel & Inputs'!$C$26,$D16),'Control Panel & Inputs'!$C$28*B34))*'Control Panel & Inputs'!$C$27 -> 30393137 | I16: =C34-$F16-MAX(0,C34-'Control Panel & Inputs'!$C$22/5-MIN(-IPMT('Control Panel & Inputs'!$C$25,2,'Control Panel & Inputs'!$C$26,$D16),'Control Panel & Inputs'!$C$28*C34))*'Control Panel & Inputs'!$C$27 -> 38962503 | J16: =D34-$F16-MAX(0,D34-'Control Panel & Inputs'!$C$22/5-MIN(-IPMT('Control Panel & Inputs'!$C$25,3,'Control Panel & Inputs'!$C$26,$D16),'Control Panel & Inputs'!$C$28*D34))*'Control Panel & Inputs'!$C$27 -> 39959160 | K16: =E34-$F16-MAX(0,E34-'Control Panel & Inputs'!$C$22/5-MIN(-IPMT('Control Panel & Inputs'!$C$25,4,'Control Panel & Inputs'!$C$26,$D16),'Control Panel & Inputs'!$C$28*E34))*'Control Panel & Inputs'!$C$27 -> 41031917 | L16: =F34-$F16-MAX(0,F34-'Control Panel & Inputs'!$C$22/5-MIN(-IPMT('Control Panel & Inputs'!$C$25,5,'Control Panel & Inputs'!$C$26,$D16),'Control Panel & Inputs'!$C$28*F34))*'Control Panel & Inputs'!$C$27+'Control Panel & Inputs'!$C$22*'Control Panel & Inputs'!$C$23 -> 56135892 | M16: =IRR(G16:L16) -> 1.2233506 | N16: =AVERAGE(B34:F34)/$F16 -> 2.5551398
... A20: $0.10/kWh @ 80% debt | B20: 0.1 | C20: 0.8 | D20: ='Control Panel & Inputs'!$C$22*$C20 -> 111600000 | E20: ='Control Panel & Inputs'!$C$22-$D20 -> 27900000 | F20: =-PMT('Control Panel & Inputs'!$C$25,'Control Panel & Inputs'!$C$26,$D20) -> 26854814 | G20: =-$E20 -> -27900000 | H20: =B38-$F20-MAX(0,B38-'Control Panel & Inputs'!$C$22/5-MIN(-IPMT('Control Panel & Inputs'!$C$25,1,'Control Panel & Inputs'!$C$26,$D20),'Control Panel & Inputs'!$C$28*B38))*'Control Panel & Inputs'!$C$27 -> 29189677 | I20: =C38-$F20-MAX(0,C38-'Control Panel & Inputs'!$C$22/5-MIN(-IPMT('Control Panel & Inputs'!$C$25,2,'Control Panel & Inputs'!$C$26,$D20),'Control Panel & Inputs'!$C$28*C38))*'Control Panel & Inputs'!$C$27 -> 37734974 | J20: =D38-$F20-MAX(0,D38-'Control Panel & Inputs'!$C$22/5-MIN(-IPMT('Control Panel & Inputs'!$C$25,3,'Control Panel & Inputs'!$C$26,$D20),'Control Panel & Inputs'!$C$28*D38))*'Control Panel & Inputs'!$C$27 -> 38707081 | K20: =E38-$F20-MAX(0,E38-'Control Panel & Inputs'!$C$22/5-MIN(-IPMT('Control Panel & Inputs'!$C$25,4,'Control Panel & Inputs'!$C$26,$D20),'Control Panel & Inputs'!$C$28*E38))*'Control Panel & Inputs'!$C$27 -> 39754796 | L20: =F38-$F20-MAX(0,F38-'Control Panel & Inputs'!$C$22/5-MIN(-IPMT('Control Panel & Inputs'!$C$25,5,'Control Panel & Inputs'!$C$26,$D20),'Control Panel & Inputs'!$C$28*F38))*'Control Panel & Inputs'!$C$27+'Control Panel & Inputs'!$C$22*'Control Panel & Inputs'!$C$23 -> 54833229 | M20: =IRR(G20:L20) -> 1.1816432 | N20: =AVERAGE(B38:F38)/$F20 -> 2.5038845
A21: Scenario EBITDA Grid (Year 1-5)
A22: Scenario | B22: Y1 EBITDA | C22: Y2 EBITDA | D22: Y3 EBITDA | E22: Y4 EBITDA | F22: Y5 EBITDA
A23: =A5 -> $0.04/kWh @ 50% debt | B23: ='5Yr Pro Forma Financials'!C$8-'5Yr Pro Forma Financials'!C$12-'5Yr Pro Forma Financials'!C$10*$B5*POWER(1+'Control Panel & Inputs'!$C$21,0) -> 62078034 | C23: ='5Yr Pro Forma Financials'!D$8-'5Yr Pro Forma Financials'!D$12-'5Yr Pro Forma Financials'!C$10*$B5*POWER(1+'Control Panel & Inputs'!$C$21,1) -> 71673824 | D23: ='5Yr Pro Forma Financials'!E$8-'5Yr Pro Forma Financials'!E$12-'5Yr Pro Forma Financials'!C$10*$B5*POWER(1+'Control Panel & Inputs'!$C$21,2) -> 72957205 | E23: ='5Yr Pro Forma Financials'!F$8-'5Yr Pro Forma Financials'!F$12-'5Yr Pro Forma Financials'!C$10*$B5*POWER(1+'Control Panel & Inputs'!$C$21,3) -> 74334014 | F23: ='5Yr Pro Forma Financials'!G$8-'5Yr Pro Forma Financials'!G$12-'5Yr Pro Forma Financials'!C$10*$B5*POWER(1+'Control Panel & Inputs'!$C$21,4) -> 75810463
A24: =A6 -> $0.04/kWh @ 60% debt | B24: ='5Yr Pro Forma Financials'!C$8-'5Yr Pro Forma Financials'!C$12-'5Yr Pro Forma Financials'!C$10*$B6*POWER(1+'Control Panel & Inputs'!$C$21,0) -> 62078034 | C24: ='5Yr Pro Forma Financials'!D$8-'5Yr Pro Forma Financials'!D$12-'5Yr Pro Forma Financials'!C$10*$B6*POWER(1+'Control Panel & Inputs'!$C$21,1) -> 71673824 | D24: ='5Yr Pro Forma Financials'!E$8-'5Yr Pro Forma Financials'!E$12-'5Yr Pro Forma Financials'!C$10*$B6*POWER(1+'Control Panel & Inputs'!$C$21,2) -> 72957205 | E24: ='5Yr Pro Forma Financials'!F$8-'5Yr Pro Forma Financials'!F$12-'5Yr Pro Forma Financials'!C$10*$B6*POWER(1+'Control Panel & Inputs'!$C$21,3) -> 74334014 | F24: ='5Yr Pro Forma Financials'!G$8-'5Yr Pro Forma Financials'!G$12-'5Yr Pro Forma Financials'!C$10*$B6*POWER(1+'Control Panel & Inputs'!$C$21,4) -> 75810463
A25: =A7 -> $0.04/kWh @ 70% debt | B25: ='5Yr Pro Forma Financials'!C$8-'5Yr Pro Forma Financials'!C$12-'5Yr Pro Forma Financials'!C$10*$B7*POWER(1+'Control Panel & Inputs'!$C$21,0) -> 62078034 | C25: ='5Yr Pro Forma Financials'!D$8-'5Yr Pro Forma Financials'!D$12-'5Yr Pro Forma Financials'!C$10*$B7*POWER(1+'Control Panel & Inputs'!$C$21,1) -> 71673824 | D25: ='5Yr Pro Forma Financials'!E$8-'5Yr Pro Forma Financials'!E$12-'5Yr Pro Forma Financials'!C$10*$B7*POWER(1+'Control Panel & Inputs'!$C$21,2) -> 72957205 | E25: ='5Yr Pro Forma Financials'!F$8-'5Yr Pro Forma Financials'!F$12-'5Yr Pro Forma Financials'!C$10*$B7*POWER(1+'Control Panel & Inputs'!$C$21,3) -> 74334014 | F25: ='5Yr Pro Forma Financials'!G$8-'5Yr Pro Forma Financials'!G$12-'5Yr Pro Forma Financials'!C$10*$B7*POWER(1+'Control Panel & Inputs'!$C$21,4) -> 75810463
A26: =A8 -> $0.04/kWh @ 80% debt | B26: ='5Yr Pro Forma Financials'!C$8-'5Yr Pro Forma Financials'!C$12-'5Yr Pro Forma Financials'!C$10*$B8*POWER(1+'Control Panel & Inputs'!$C$21,0) -> 62078034 | C26: ='5Yr Pro Forma Financials'!D$8-'5Yr Pro Forma Financials'!D$12-'5Yr Pro Forma Financials'!C$10*$B8*POWER(1+'Control Panel & Inputs'!$C$21,1) -> 71673824 | D26: ='5Yr Pro Forma Financials'!E$8-'5Yr Pro Forma Financials'!E$12-'5Yr Pro Forma Financials'!C$10*$B8*POWER(1+'Control Panel & Inputs'!$C$21,2) -> 72957205 | E26: ='5Yr Pro Forma Financials'!F$8-'5Yr Pro Forma Financials'!F$12-'5Yr Pro Forma Financials'!C$10*$B8*POWER(1+'Control Panel & Inputs'!$C$21,3) -> 74334014 | F26: ='5Yr Pro Forma Financials'!G$8-'5Yr Pro Forma Financials'!G$12-'5Yr Pro Forma Financials'!C$10*$B8*POWER(1+'Control Panel & Inputs'!$C$21,4) -> 75810463
A27: =A9 -> $0.06/kWh @ 50% debt | B27: ='5Yr Pro Forma Financials'!C$8-'5Yr Pro Forma Financials'!C$12-'5Yr Pro Forma Financials'!C$10*$B9*POWER(1+'Control Panel & Inputs'!$C$21,0) -> 60755550 | C27: ='5Yr Pro Forma Financials'!D$8-'5Yr Pro Forma Financials'!D$12-'5Yr Pro Forma Financials'!C$10*$B9*POWER(1+'Control Panel & Inputs'!$C$21,1) -> 70324891 | D27: ='5Yr Pro Forma Financials'!E$8-'5Yr Pro Forma Financials'!E$12-'5Yr Pro Forma Financials'!C$10*$B9*POWER(1+'Control Panel & Inputs'!$C$21,2) -> 71581294 | E27: ='5Yr Pro Forma Financials'!F$8-'5Yr Pro Forma Financials'!F$12-'5Yr Pro Forma Financials'!C$10*$B9*POWER(1+'Control Panel & Inputs'!$C$21,3) -> 72930584 | F27: ='5Yr Pro Forma Financials'!G$8-'5Yr Pro Forma Financials'!G$12-'5Yr Pro Forma Financials'!C$10*$B9*POWER(1+'Control Panel & Inputs'!$C$21,4) -> 74378964
A28: =A10 -> $0.06/kWh @ 60% debt | B28: ='5Yr Pro Forma Financials'!C$8-'5Yr Pro Forma Financials'!C$12-'5Yr Pro Forma Financials'!C$10*$B10*POWER(1+'Control Panel & Inputs'!$C$21,0) -> 60755550 | C28: ='5Yr Pro Forma Financials'!D$8-'5Yr Pro Forma Financials'!D$12-'5Yr Pro Forma Financials'!C$10*$B10*POWER(1+'Control Panel & Inputs'!$C$21,1) -> 70324891 | D28: ='5Yr Pro Forma Financials'!E$8-'5Yr Pro Forma Financials'!E$12-'5Yr Pro Forma Financials'!C$10*$B10*POWER(1+'Control Panel & Inputs'!$C$21,2) -> 71581294 | E28: ='5Yr Pro Forma Financials'!F$8-'5Yr Pro Forma Financials'!F$12-'5Yr Pro Forma Financials'!C$10*$B10*POWER(1+'Control Panel & Inputs'!$C$21,3) -> 72930584 | F28: ='5Yr Pro Forma Financials'!G$8-'5Yr Pro Forma Financials'!G$12-'5Yr Pro Forma Financials'!C$10*$B10*POWER(1+'Control Panel & Inputs'!$C$21,4) -> 74378964
A29: =A11 -> $0.06/kWh @ 70% debt | B29: ='5Yr Pro Forma Financials'!C$8-'5Yr Pro Forma Financials'!C$12-'5Yr Pro Forma Financials'!C$10*$B11*POWER(1+'Control Panel & Inputs'!$C$21,0) -> 60755550 | C29: ='5Yr Pro Forma Financials'!D$8-'5Yr Pro Forma Financials'!D$12-'5Yr Pro Forma Financials'!C$10*$B11*POWER(1+'Control Panel & Inputs'!$C$21,1) -> 70324891 | D29: ='5Yr Pro Forma Financials'!E$8-'5Yr Pro Forma Financials'!E$12-'5Yr Pro Forma Financials'!C$10*$B11*POWER(1+'Control Panel & Inputs'!$C$21,2) -> 71581294 | E29: ='5Yr Pro Forma Financials'!F$8-'5Yr Pro Forma Financials'!F$12-'5Yr Pro Forma Financials'!C$10*$B11*POWER(1+'Control Panel & Inputs'!$C$21,3) -> 72930584 | F29: ='5Yr Pro Forma Financials'!G$8-'5Yr Pro Forma Financials'!G$12-'5Yr Pro Forma Financials'!C$10*$B11*POWER(1+'Control Panel & Inputs'!$C$21,4) -> 74378964
A30: =A12 -> $0.06/kWh @ 80% debt | B30: ='5Yr Pro Forma Financials'!C$8-'5Yr Pro Forma Financials'!C$12-'5Yr Pro Forma Financials'!C$10*$B12*POWER(1+'Control Panel & Inputs'!$C$21,0) -> 60755550 | C30: ='5Yr Pro Forma Financials'!D$8-'5Yr Pro Forma Financials'!D$12-'5Yr Pro Forma Financials'!C$10*$B12*POWER(1+'Control Panel & Inputs'!$C$21,1) -> 70324891 | D30: ='5Yr Pro Forma Financials'!E$8-'5Yr Pro Forma Financials'!E$12-'5Yr Pro Forma Financials'!C$10*$B12*POWER(1+'Control Panel & Inputs'!$C$21,2) -> 71581294 | E30: ='5Yr Pro Forma Financials'!F$8-'5Yr Pro Forma Financials'!F$12-'5Yr Pro Forma Financials'!C$10*$B12*POWER(1+'Control Panel & Inputs'!$C$21,3) -> 72930584 | F30: ='5Yr Pro Forma Financials'!G$8-'5Yr Pro Forma Financials'!G$12-'5Yr Pro Forma Financials'!C$10*$B12*POWER(1+'Control Panel & Inputs'!$C$21,4) -> 74378964
A31: =A13 -> $0.08/kWh @ 50% debt | B31: ='5Yr Pro Forma Financials'!C$8-'5Yr Pro Forma Financials'!C$12-'5Yr Pro Forma Financials'!C$10*$B13*POWER(1+'Control Panel & Inputs'!$C$21,0) -> 59433067 | C31: ='5Yr Pro Forma Financials'!D$8-'5Yr Pro Forma Financials'!D$12-'5Yr Pro Forma Financials'!C$10*$B13*POWER(1+'Control Panel & Inputs'!$C$21,1) -> 68975958 | D31: ='5Yr Pro Forma Financials'!E$8-'5Yr Pro Forma Financials'!E$12-'5Yr Pro Forma Financials'!C$10*$B13*POWER(1+'Control Panel & Inputs'!$C$21,2) -> 70205382 | E31: ='5Yr Pro Forma Financials'!F$8-'5Yr Pro Forma Financials'!F$12-'5Yr Pro Forma Financials'!C$10*$B13*POWER(1+'Control Panel & Inputs'!$C$21,3) -> 71527154 | F31: ='5Yr Pro Forma Financials'!G$8-'5Yr Pro Forma Financials'!G$12-'5Yr Pro Forma Financials'!C$10*$B13*POWER(1+'Control Panel & Inputs'!$C$21,4) -> 72947466
A32: =A14 -> $0.08/kWh @ 60% debt | B32: ='5Yr Pro Forma Financials'!C$8-'5Yr Pro Forma Financials'!C$12-'5Yr Pro Forma Financials'!C$10*$B14*POWER(1+'Control Panel & Inputs'!$C$21,0) -> 59433067 | C32: ='5Yr Pro Forma Financials'!D$8-'5Yr Pro Forma Financials'!D$12-'5Yr Pro Forma Financials'!C$10*$B14*POWER(1+'Control Panel & Inputs'!$C$21,1) -> 68975958 | D32: ='5Yr Pro Forma Financials'!E$8-'5Yr Pro Forma Financials'!E$12-'5Yr Pro Forma Financials'!C$10*$B14*POWER(1+'Control Panel & Inputs'!$C$21,2) -> 70205382 | E32: ='5Yr Pro Forma Financials'!F$8-'5Yr Pro Forma Financials'!F$12-'5Yr Pro Forma Financials'!C$10*$B14*POWER(1+'Control Panel & Inputs'!$C$21,3) -> 71527154 | F32: ='5Yr Pro Forma Financials'!G$8-'5Yr Pro Forma Financials'!G$12-'5Yr Pro Forma Financials'!C$10*$B14*POWER(1+'Control Panel & Inputs'!$C$21,4) -> 72947466
A33: =A15 -> $0.08/kWh @ 70% debt | B33: ='5Yr Pro Forma Financials'!C$8-'5Yr Pro Forma Financials'!C$12-'5Yr Pro Forma Financials'!C$10*$B15*POWER(1+'Control Panel & Inputs'!$C$21,0) -> 59433067 | C33: ='5Yr Pro Forma Financials'!D$8-'5Yr Pro Forma Financials'!D$12-'5Yr Pro Forma Financials'!C$10*$B15*POWER(1+'Control Panel & Inputs'!$C$21,1) -> 68975958 | D33: ='5Yr Pro Forma Financials'!E$8-'5Yr Pro Forma Financials'!E$12-'5Yr Pro Forma Financials'!C$10*$B15*POWER(1+'Control Panel & Inputs'!$C$21,2) -> 70205382 | E33: ='5Yr Pro Forma Financials'!F$8-'5Yr Pro Forma Financials'!F$12-'5Yr Pro Forma Financials'!C$10*$B15*POWER(1+'Control Panel & Inputs'!$C$21,3) -> 71527154 | F33: ='5Yr Pro Forma Financials'!G$8-'5Yr Pro Forma Financials'!G$12-'5Yr Pro Forma Financials'!C$10*$B15*POWER(1+'Control Panel & Inputs'!$C$21,4) -> 72947466
A34: =A16 -> $0.08/kWh @ 80% debt | B34: ='5Yr Pro Forma Financials'!C$8-'5Yr Pro Forma Financials'!C$12-'5Yr Pro Forma Financials'!C$10*$B16*POWER(1+'Control Panel & Inputs'!$C$21,0) -> 59433067 | C34: ='5Yr Pro Forma Financials'!D$8-'5Yr Pro Forma Financials'!D$12-'5Yr Pro Forma Financials'!C$10*$B16*POWER(1+'Control Panel & Inputs'!$C$21,1) -> 68975958 | D34: ='5Yr Pro Forma Financials'!E$8-'5Yr Pro Forma Financials'!E$12-'5Yr Pro Forma Financials'!C$10*$B16*POWER(1+'Control Panel & Inputs'!$C$21,2) -> 70205382 | E34: ='5Yr Pro Forma Financials'!F$8-'5Yr Pro Forma Financials'!F$12-'5Yr Pro Forma Financials'!C$10*$B16*POWER(1+'Control Panel & Inputs'!$C$21,3) -> 71527154 | F34: ='5Yr Pro Forma Financials'!G$8-'5Yr Pro Forma Financials'!G$12-'5Yr Pro Forma Financials'!C$10*$B16*POWER(1+'Control Panel & Inputs'!$C$21,4) -> 72947466
... A38: =A20 -> $0.10/kWh @ 80% debt | B38: ='5Yr Pro Forma Financials'!C$8-'5Yr Pro Forma Financials'!C$12-'5Yr Pro Forma Financials'!C$10*$B20*POWER(1+'Control Panel & Inputs'!$C$21,0) -> 58110584 | C38: ='5Yr Pro Forma Financials'!D$8-'5Yr Pro Forma Financials'!D$12-'5Yr Pro Forma Financials'!C$10*$B20*POWER(1+'Control Panel & Inputs'!$C$21,1) -> 67627026 | D38: ='5Yr Pro Forma Financials'!E$8-'5Yr Pro Forma Financials'!E$12-'5Yr Pro Forma Financials'!C$10*$B20*POWER(1+'Control Panel & Inputs'!$C$21,2) -> 68829470 | E38: ='5Yr Pro Forma Financials'!F$8-'5Yr Pro Forma Financials'!F$12-'5Yr Pro Forma Financials'!C$10*$B20*POWER(1+'Control Panel & Inputs'!$C$21,3) -> 70123724 | F38: ='5Yr Pro Forma Financials'!G$8-'5Yr Pro Forma Financials'!G$12-'5Yr Pro Forma Financials'!C$10*$B20*POWER(1+'Control Panel & Inputs'!$C$21,4) -> 71515968

Sheet Sensitivity Matrices
A1: 5-Year Leveraged Sensitivity Matrices
A2: Power tariff ($0.04 - $0.10/kWh) vs. debt ratio (50% - 80%) — every cell is a live link to the Sensitivity Engine
A4: Matrix 1: Leveraged 5-Year Equity IRR (%)
A5: Power Tariff ($/kWh) | B5: 50% Debt | C5: 60% Debt | D5: 70% Debt | E5: 80% Debt
A6: $0.04 / kWh | B6: ='Sensitivity Engine'!M5 -> 0.64397875 | C6: ='Sensitivity Engine'!M6 -> 0.76238252 | D6: ='Sensitivity Engine'!M7 -> 0.95059746 | E6: ='Sensitivity Engine'!M8 -> 1.3067984
A7: $0.06 / kWh | B7: ='Sensitivity Engine'!M9 -> 0.62563439 | C7: ='Sensitivity Engine'!M10 -> 0.74012926 | D7: ='Sensitivity Engine'!M11 -> 0.92187536 | E7: ='Sensitivity Engine'!M12 -> 1.2650683
A8: $0.08 / kWh | B8: ='Sensitivity Engine'!M13 -> 0.60723023 | C8: ='Sensitivity Engine'!M14 -> 0.71781947 | D8: ='Sensitivity Engine'!M15 -> 0.89311254 | E8: ='Sensitivity Engine'!M16 -> 1.2233506
A9: $0.10 / kWh | B9: ='Sensitivity Engine'!M17 -> 0.58876284 | C9: ='Sensitivity Engine'!M18 -> 0.6954493 | D9: ='Sensitivity Engine'!M19 -> 0.86430503 | E9: ='Sensitivity Engine'!M20 -> 1.1816432
A12: Matrix 2: Average Debt Service Coverage Ratio (DSCR)
A13: Power Tariff ($/kWh) | B13: 50% Debt | C13: 60% Debt | D13: 70% Debt | E13: 80% Debt
A14: $0.04 / kWh | B14: ='Sensitivity Engine'!N5 -> 4.2522406 | C14: ='Sensitivity Engine'!N6 -> 3.5435338 | D14: ='Sensitivity Engine'!N7 -> 3.0373147 | E14: ='Sensitivity Engine'!N8 -> 2.6576504
A15: $0.06 / kWh | B15: ='Sensitivity Engine'!N9 -> 4.1702322 | C15: ='Sensitivity Engine'!N10 -> 3.4751935 | D15: ='Sensitivity Engine'!N11 -> 2.9787373 | E15: ='Sensitivity Engine'!N12 -> 2.6063951
A16: $0.08 / kWh | B16: ='Sensitivity Engine'!N13 -> 4.0882237 | C16: ='Sensitivity Engine'!N14 -> 3.4068531 | D16: ='Sensitivity Engine'!N15 -> 2.9201598 | E16: ='Sensitivity Engine'!N16 -> 2.5551398
A17: $0.10 / kWh | B17: ='Sensitivity Engine'!N17 -> 4.0062153 | C17: ='Sensitivity Engine'!N18 -> 3.3385127 | D17: ='Sensitivity Engine'!N19 -> 2.8615823 | E17: ='Sensitivity Engine'!N20 -> 2.5038845
